chrontext-0.9.16.dist-info/METADATA
chrontext-0.9.16.dist-info/WHEEL
chrontext-0.9.16.dist-info/licenses/LICENSE
chrontext/__init__.py
chrontext/vq/__init__.pyi
chrontext/vq/__init__.py
chrontext/.gitignore
chrontext/py.typed
chrontext/chrontext.pyi
chrontext/chrontext.abi3.so
chrontext-0.9.16.dist-info/RECORD
