Metadata-Version: 2.3
Name: chrontext
Version: 0.9.16
Classifier: Development Status :: 4 - Beta
Classifier: License :: OSI Approved :: Apache Software License
Classifier: Programming Language :: Python :: 3 :: Only
Classifier: Programming Language :: Python :: 3.9
Classifier: Programming Language :: Python :: 3.10
Classifier: Programming Language :: Python :: 3.11
Classifier: Programming Language :: Rust
Classifier: Topic :: Database :: Database Engines/Servers
Classifier: Topic :: Scientific/Engineering
Requires-Dist: polars >=0.20.2
Requires-Dist: pyarrow >=7.0.0
Requires-Dist: pandas
Requires-Dist: sqlalchemy >=2.0.31
Requires-Dist: sqlalchemy-bigquery >=1.11.0
Requires-Dist: databricks-sqlalchemy >=2.0.4
Requires-Dist: databricks-sql-connector >=3.3.0
Requires-Dist: pyoxigraph >=0.4.2
License-File: LICENSE
Summary: Hybrid SPARQL query engine for timeseries data
Keywords: rdf,graph,arrow,sparql,timeseries
Author-email: Magnus Bakken <magnus@data-treehouse.com>
Requires-Python: >=3.9
Project-URL: Homepage, https://github.com/DataTreehouse/chrontext
Project-URL: Documentation, https://datatreehouse.github.io/chrontext/chrontext/chrontext.html
Project-URL: Repository, https://github.com/DataTreehouse/chrontext
Project-URL: Changelog, https://github.com/DataTreehouse/chrontext/releases
